pyrplidarsdk/__init__.py
pyrplidarsdk/rplidar_wrapper.cpython-312-aarch64-linux-gnu.so
pyrplidarsdk/utils.py
pyrplidarsdk-0.1.1.dist-info/METADATA
pyrplidarsdk-0.1.1.dist-info/WHEEL
pyrplidarsdk-0.1.1.dist-info/RECORD
pyrplidarsdk-0.1.1.dist-info/licenses/LICENSE
