Metadata-Version: 2.2
Name: pyrplidarsdk
Version: 0.1.1
Summary: Python wrapper for RPLIDAR SDK using nanobind
Author-Email: "Dexmate Inc." <contact@dexmate.ai>
License: MIT
Classifier: Development Status :: 4 - Beta
Classifier: Intended Audience :: Developers
Classifier: License :: OSI Approved :: MIT License
Classifier: Operating System :: POSIX :: Linux
Classifier: Operating System :: Microsoft :: Windows
Classifier: Operating System :: MacOS
Classifier: Programming Language :: Python :: 3.10
Classifier: Programming Language :: Python :: 3.11
Classifier: Programming Language :: Python :: 3.12
Classifier: Programming Language :: Python :: 3.13
Classifier: Programming Language :: C++
Classifier: Topic :: Scientific/Engineering
Classifier: Topic :: Software Development :: Libraries :: Python Modules
Project-URL: Homepage, https://github.com/dexmate-ai/pyrplidarsdk
Project-URL: Repository, https://github.com/dexmate-ai/pyrplidarsdk.git
Project-URL: Issues, https://github.com/dexmate-ai/pyrplidarsdk/issues
Requires-Python: >=3.10
Requires-Dist: numpy
Provides-Extra: dev
Requires-Dist: build; extra == "dev"
Requires-Dist: twine; extra == "dev"
